{
  "data": {
    "userId": 18,
    "sessions": [
      {
        "day": 1,
        "sessionLength": 32
      },
      {
        "day": 2,
        "sessionLength": 42
      },
      {
        "day": 3,
        "sessionLength": 52
      },
      {
        "day": 4,
        "sessionLength": 36
      },
      {
        "day": 5,
        "sessionLength": 27
      },
      {
        "day": 6,
        "sessionLength": 55
      },
      {
        "day": 7,
        "sessionLength": 48
      }
    ]
  }
}
